kingbird/__init__.py
kingbird/version.py
kingbird/api/README.rst
kingbird/api/__init__.py
kingbird/api/api_config.py
kingbird/api/app.py
kingbird/api/enforcer.py
kingbird/api/controllers/README.rst
kingbird/api/controllers/__init__.py
kingbird/api/controllers/restcomm.py
kingbird/api/controllers/root.py
kingbird/api/controllers/v1/README.rst
kingbird/api/controllers/v1/__init__.py
kingbird/api/controllers/v1/quota_class.py
kingbird/api/controllers/v1/quota_manager.py
kingbird/api/controllers/v1/root.py
kingbird/api/controllers/v1/sync_manager.py
kingbird/cmd/README.rst
kingbird/cmd/__init__.py
kingbird/cmd/api.py
kingbird/cmd/engine.py
kingbird/cmd/manage.py
kingbird/common/__init__.py
kingbird/common/config.py
kingbird/common/consts.py
kingbird/common/context.py
kingbird/common/endpoint_cache.py
kingbird/common/exceptions.py
kingbird/common/i18n.py
kingbird/common/manager.py
kingbird/common/messaging.py
kingbird/common/policy.py
kingbird/common/serializer.py
kingbird/common/utils.py
kingbird/common/version.py
kingbird/db/__init__.py
kingbird/db/api.py
kingbird/db/utils.py
kingbird/db/sqlalchemy/__init__.py
kingbird/db/sqlalchemy/api.py
kingbird/db/sqlalchemy/migration.py
kingbird/db/sqlalchemy/models.py
kingbird/db/sqlalchemy/migrate_repo/README
kingbird/db/sqlalchemy/migrate_repo/__init__.py
kingbird/db/sqlalchemy/migrate_repo/manage.py
kingbird/db/sqlalchemy/migrate_repo/migrate.cfg
kingbird/db/sqlalchemy/migrate_repo/versions/001_first_version.py
kingbird/db/sqlalchemy/migrate_repo/versions/002_sync_lock.py
kingbird/db/sqlalchemy/migrate_repo/versions/003_quota_class.py
kingbird/db/sqlalchemy/migrate_repo/versions/004_default_quota_class.py
kingbird/db/sqlalchemy/migrate_repo/versions/005_service.py
kingbird/db/sqlalchemy/migrate_repo/versions/006_sync_job.py
kingbird/db/sqlalchemy/migrate_repo/versions/__init__.py
kingbird/drivers/README.rst
kingbird/drivers/__init__.py
kingbird/drivers/base.py
kingbird-1.3.0.dist-info/DESCRIPTION.rst
kingbird-1.3.0.dist-info/METADATA
kingbird-1.3.0.dist-info/RECORD
kingbird-1.3.0.dist-info/WHEEL
kingbird-1.3.0.dist-info/entry_points.txt
kingbird-1.3.0.dist-info/metadata.json
kingbird-1.3.0.dist-info/pbr.json
kingbird-1.3.0.dist-info/top_level.txt
