Metadata-Version: 2.0
Name: kingbird
Version: 1.3.0
Summary: Kingbird is a centralised synchronization service for multi-region OpenStack deployments.
Home-page: http://www.openstack.org/
Author: OpenStack
Author-email: openstack-dev@lists.openstack.org
License: UNKNOWN
Platform: UNKNOWN
Classifier: Environment :: OpenStack
Classifier: Intended Audience :: Information Technology
Classifier: Intended Audience :: System Administrators
Classifier: License :: OSI Approved :: Apache Software License
Classifier: Operating System :: POSIX :: Linux
Classifier: Programming Language :: Python
Classifier: Programming Language :: Python :: 2
Classifier: Programming Language :: Python :: 2.7
Classifier: Programming Language :: Python :: 3
Classifier: Programming Language :: Python :: 3.3
Classifier: Programming Language :: Python :: 3.4
Requires-Dist: pbr (!=2.1.0,>=2.0.0)
Requires-Dist: Babel (!=2.4.0,>=2.3.4)
Requires-Dist: Paste (>=2.0.2)
Requires-Dist: PasteDeploy (>=1.5.0)
Requires-Dist: Routes (>=2.3.1)
Requires-Dist: debtcollector (>=1.2.0)
Requires-Dist: eventlet (!=0.18.3,!=0.20.1,<0.21.0,>=0.18.2)
Requires-Dist: pecan (!=1.0.2,!=1.0.3,!=1.0.4,!=1.2,>=1.0.0)
Requires-Dist: greenlet (>=0.4.10)
Requires-Dist: httplib2 (>=0.9.1)
Requires-Dist: requests (>=2.14.2)
Requires-Dist: Jinja2 (>=2.10)
Requires-Dist: keystonemiddleware (>=4.17.0)
Requires-Dist: netaddr (>=0.7.18)
Requires-Dist: retrying (!=1.3.0,>=1.2.3)
Requires-Dist: SQLAlchemy (!=1.1.5,!=1.1.6,!=1.1.7,!=1.1.8,>=1.0.10)
Requires-Dist: WebOb (>=1.7.1)
Requires-Dist: alembic (>=0.8.10)
Requires-Dist: six (>=1.10.0)
Requires-Dist: stevedore (>=1.20.0)
Requires-Dist: oslo.concurrency (>=3.25.0)
Requires-Dist: oslo.config (>=5.1.0)
Requires-Dist: oslo.context (>=2.19.2)
Requires-Dist: oslo.db (>=4.27.0)
Requires-Dist: oslo.i18n (>=3.15.3)
Requires-Dist: oslo.log (>=3.36.0)
Requires-Dist: oslo.messaging (>=5.29.0)
Requires-Dist: oslo.middleware (>=3.31.0)
Requires-Dist: oslo.policy (>=1.30.0)
Requires-Dist: oslo.rootwrap (>=5.8.0)
Requires-Dist: oslo.serialization (!=2.19.1,>=2.18.0)
Requires-Dist: oslo.service (!=1.28.1,>=1.24.0)
Requires-Dist: oslo.utils (>=3.33.0)
Requires-Dist: oslo.versionedobjects (>=1.31.2)
Requires-Dist: sqlalchemy-migrate (>=0.11.0)
Requires-Dist: python-openstackclient (>=3.12.0)
Requires-Dist: python-neutronclient (>=6.7.0)
Requires-Dist: python-cinderclient (>=3.3.0)
Requires-Dist: python-novaclient (>=9.1.0)
Requires-Dist: python-keystoneclient (>=3.8.0)
